septem_circumstantiae/__init__.py
septem_circumstantiae/events.py
septem_circumstantiae/resources/__init__.py
septem_circumstantiae/resources/by_what_means.text
septem_circumstantiae/resources/how.text
septem_circumstantiae/resources/what.text
septem_circumstantiae/resources/when.text
septem_circumstantiae/resources/where.text
septem_circumstantiae/resources/who.text
septem_circumstantiae/resources/why.text
septem_circumstantiae-0.0.11.dist-info/LICENSE
septem_circumstantiae-0.0.11.dist-info/METADATA
septem_circumstantiae-0.0.11.dist-info/WHEEL
septem_circumstantiae-0.0.11.dist-info/top_level.txt
septem_circumstantiae-0.0.11.dist-info/RECORD
