Metadata-Version: 2.1
Name: septem-circumstantiae
Version: 0.0.11
Summary: Septem Circumstantiae
Author-email: Alexander Fedotov <alex.fedotov@aol.com>
Project-URL: Homepage, https://github.com/septem-circumstantiae/septem-circumstantiae
Project-URL: Bug Tracker, https://github.com/septem-circumstantiae/septem-circumstantiae/issues
Classifier: Programming Language :: Python :: 3
Classifier: License :: OSI Approved :: MIT License
Classifier: Operating System :: OS Independent
Requires-Python: >=3.10
License-File: LICENSE
